{"errors":[],"warnings":[],"namedChunkGroups":{"polyfill":{"chunks":[2,0,8],"assets":["webpack-runtime-750cea1153257ae2f0d1.js","webpack-runtime-750cea1153257ae2f0d1.js.map","commons-462d72eaa519ccf6a1b3.js","commons-462d72eaa519ccf6a1b3.js.map","polyfill-4bf749adb93e95a0c53b.js","polyfill-4bf749adb93e95a0c53b.js.map"],"children":{},"childAssets":{}},"app":{"chunks":[2,7,4],"assets":["webpack-runtime-750cea1153257ae2f0d1.js","webpack-runtime-750cea1153257ae2f0d1.js.map","framework-3f1761df32134e8bc537.js","framework-3f1761df32134e8bc537.js.map","app-559354e484bf586484aa.js","app-559354e484bf586484aa.js.map"],"children":{},"childAssets":{}},"component---src-pages-404-js":{"chunks":[1,0,5],"assets":["styles.80822aa590690bb54219.css","styles-c2fe8482057191dca484.js","styles-c2fe8482057191dca484.js.map","commons-462d72eaa519ccf6a1b3.js","commons-462d72eaa519ccf6a1b3.js.map","component---src-pages-404-js-aa60ee366749062461ce.js","component---src-pages-404-js-aa60ee366749062461ce.js.map"],"children":{},"childAssets":{}},"component---src-pages-index-js":{"chunks":[1,3,0,6],"assets":["styles.80822aa590690bb54219.css","styles-c2fe8482057191dca484.js","styles-c2fe8482057191dca484.js.map","2edb282b-2ec03904b6ba0175bc57.js","2edb282b-2ec03904b6ba0175bc57.js.map","commons-462d72eaa519ccf6a1b3.js","commons-462d72eaa519ccf6a1b3.js.map","component---src-pages-index-js-226a3b5e0e94dfda3aa2.js","component---src-pages-index-js-226a3b5e0e94dfda3aa2.js.map"],"children":{},"childAssets":{}}},"assetsByChunkName":{"polyfill":["webpack-runtime-750cea1153257ae2f0d1.js","commons-462d72eaa519ccf6a1b3.js","polyfill-4bf749adb93e95a0c53b.js"],"app":["webpack-runtime-750cea1153257ae2f0d1.js","framework-3f1761df32134e8bc537.js","app-559354e484bf586484aa.js"],"component---src-pages-404-js":["styles.80822aa590690bb54219.css","styles-c2fe8482057191dca484.js","commons-462d72eaa519ccf6a1b3.js","component---src-pages-404-js-aa60ee366749062461ce.js"],"component---src-pages-index-js":["styles.80822aa590690bb54219.css","styles-c2fe8482057191dca484.js","2edb282b-2ec03904b6ba0175bc57.js","commons-462d72eaa519ccf6a1b3.js","component---src-pages-index-js-226a3b5e0e94dfda3aa2.js"]}}